Metadata-Version: 2.1
Name: HttpClientMultipart
Version: 0.0.1
Summary: This package implement client to upload file using HTTP multipart
Home-page: https://github.com/mauricelambert/HttpClientMultipart
Author: Maurice Lambert
Author-email: mauricelambert434@gmail.com
Maintainer: Maurice Lambert
Maintainer-email: mauricelambert434@gmail.com
License: GPL-3.0 License
Download-URL: https://mauricelambert.github.io/python/code/HttpClientMultipart.pyz
Project-URL: Executable, https://mauricelambert.github.io/info/python/code/HttpClientMultipart.pyz
Project-URL: Documentation, https://mauricelambert.github.io/info/python/code/HttpClientMultipart.html
Keywords: Multipart,HTTP,form-data,http.client,urllib
Platform: Windows
Platform: Linux
Platform: MacOS
Classifier: Programming Language :: Python
Classifier: Development Status :: 5 - Production/Stable
Classifier: Environment :: Console
Classifier: Operating System :: MacOS :: MacOS X
Classifier: Operating System :: Microsoft :: Windows
Classifier: Operating System :: POSIX
Classifier: Natural Language :: English
Classifier: Programming Language :: Python :: 3.8
Classifier: Topic :: Internet :: WWW/HTTP
Requires-Python: >=3.6
